meshRW/__init__.py
meshRW/configMESH.py
meshRW/dbmsh.py
meshRW/dbvtk.py
meshRW/fileio.py
meshRW/msh.py
meshRW/msh2.py
meshRW/various.py
meshRW/vtk.py
meshRW/vtk2.py
meshRW/writerClass.py
meshRW/tests/__init__.py
meshRW/tests/test_dbmsh.py
meshRW/tests/test_dbvtk.py
meshRW/tests/test_fileio.py
meshRW/tests/test_msh.py
meshRW/tests/test_various.py
meshRW/tests/test_vtk.py
meshRW/tests/test_data/debug.h5
meshRW/tests/test_data/mesh2Dref.msh
meshRW/tests/test_data/mesh3Dref.msh
meshrw-1.5.2.dist-info/METADATA
meshrw-1.5.2.dist-info/WHEEL
meshrw-1.5.2.dist-info/licenses/AUTHORS
meshrw-1.5.2.dist-info/licenses/LICENSE
meshrw-1.5.2.dist-info/RECORD
