Metadata-Version: 2.4
Name: meshRW
Version: 1.5.2
Summary: meshRW is a Python module that proposes basic readers and writers for msh (gmsh) and vtk (Paraview).
Project-URL: Homepage, https://github.com/luclaurent/meshRW
Project-URL: Repository, https://github.com/luclaurent/meshRW
Project-URL: Issues, https://github.com/luclaurent/meshRW/issues
Author-email: "L. Laurent" <luc.laurent@lecnam.net>
License: MIT License
License-File: AUTHORS
License-File: LICENSE
Classifier: License :: OSI Approved :: MIT License
Classifier: Operating System :: OS Independent
Classifier: Programming Language :: Python :: 3
Requires-Python: >=3.8
Requires-Dist: gmsh
Requires-Dist: loguru
Requires-Dist: lxml
Requires-Dist: numpy
Requires-Dist: pytest
Requires-Dist: pytest-cov
Requires-Dist: vtk
